tokamino/__init__.py
tokamino/__main__.py
tokamino/_api.py
tokamino/_errors.py
tokamino/_lib.py
tokamino/_logging.py
tokamino/_subpackages.py
tokamino/_types.py
tokamino/libtokamino.dylib
tokamino/mlx.metallib
tokamino/wrapper.py
tokamino/chat_session/__init__.py
tokamino/chat_session/output.py
tokamino/chat_session/session.py
tokamino/cli/__init__.py
tokamino/cli/stats.py
tokamino/cli/stream.py
tokamino/converter/__init__.py
tokamino/converter/converter.py
tokamino/examples/chat_session/basic.py
tokamino/examples/chat_session/multi_turn.py
tokamino/examples/chat_session/streaming.py
tokamino/examples/converter/basic.py
tokamino/examples/converter/progress.py
tokamino/examples/converter/quantized.py
tokamino/examples/storage/check_cached.py
tokamino/examples/storage/list_models.py
tokamino/examples/template/basic.py
tokamino/examples/template/chain_of_thought.py
tokamino/examples/template/few_shot.py
tokamino/examples/template/load_template.py
tokamino/examples/template/rag.py
tokamino/examples/template/tool_use.py
tokamino/examples/template/etc/chain_of_thought.j2
tokamino/examples/template/etc/extract.j2
tokamino/examples/template/etc/few_shot.j2
tokamino/examples/template/etc/rag.j2
tokamino/examples/template/etc/summarize.j2
tokamino/examples/template/etc/tool_use.j2
tokamino/examples/tokenizer/basic.py
tokamino/examples/tokenizer/count_tokens.py
tokamino/model/__init__.py
tokamino/model/describe.py
tokamino/ops/__init__.py
tokamino/ops/_bindings.py
tokamino/ops/_errors.py
tokamino/storage/__init__.py
tokamino/storage/base.py
tokamino/storage/local.py
tokamino/template/__init__.py
tokamino/template/template.py
tokamino/tokenizer/__init__.py
tokamino/tokenizer/template.py
tokamino/tokenizer/token_array.py
tokamino/tokenizer/tokenizer.py
tokamino-0.0.2.dist-info/METADATA
tokamino-0.0.2.dist-info/WHEEL
tokamino-0.0.2.dist-info/entry_points.txt
tokamino-0.0.2.dist-info/RECORD
