Metadata-Version: 2.4
Name: tokamino
Version: 0.0.2
Summary: High-performance LLM inference with zero dependencies
Requires-Python: >=3.10
Provides-Extra: test
Requires-Dist: accelerate>=0.30; extra == 'test'
Requires-Dist: numpy>=1.21; extra == 'test'
Requires-Dist: pytest-xdist>=3.0; extra == 'test'
Requires-Dist: pytest>=7.0; extra == 'test'
Requires-Dist: torch>=2.0; extra == 'test'
Requires-Dist: transformers>=4.40; extra == 'test'
